[
    {
    "id": 1,
    "name": "image1",
    "image": "https://via.placeholder.com/300.png/rrr/fff"
    },
    {
    "id": 2,
    "name": "image2",
    "image": "https://via.placeholder.com/300.png/888/ggg"
    },
    {
    "id": 3,
    "name": "image3",
    "image": "https://via.placeholder.com/300.png/aaa/fff"
    },
    {
    "id": 4,
    "name": "image4",
    "image": "https://via.placeholder.com/300.png/000/fff"
    },
    {
    "id": 5,
    "name": "image5",
    "image": "https://via.placeholder.com/300.png/mmm/fff"
    },
    {
    "id": 6,
    "name": "image6",
    "image": "https://via.placeholder.com/300.png/444/fff"
    },
    {
    "id": 7,
    "name": "image7",
    "image": "https://via.placeholder.com/300.png/09f/fff"
    }
    
        
    
]